filepmon/__init__.py
filepmon/pgf.py
filepmon_karjakak-0.2.1.dist-info/METADATA
filepmon_karjakak-0.2.1.dist-info/WHEEL
filepmon_karjakak-0.2.1.dist-info/entry_points.txt
filepmon_karjakak-0.2.1.dist-info/top_level.txt
filepmon_karjakak-0.2.1.dist-info/RECORD
