Metadata-Version: 2.1
Name: filepmon-karjakak
Version: 0.2.1
Summary: File permission view and changer.
Home-page: https://github.com/kakkarja/FilePermission
Author: karjakak
Author-email: kakkarja.github@gmail.com
License: BSD3 License
Classifier: Environment :: MacOS X
Classifier: Programming Language :: Python :: 3.10
Classifier: License :: OSI Approved :: BSD License
Requires-Python: >=3.10
